[
    {
        "client_msg_id": "78E1DA76-72B4-4022-AF06-D26770B3DEC3",
        "type": "message",
        "text": "Dang it, we timed this last baby wrong!",
        "user": "U03M8T9K6SU",
        "ts": "1697924861.911899",
        "blocks": [
            {
                "type": "rich_text",
                "block_id": "pYttB",
                "elements": [
                    {
                        "type": "rich_text_section",
                        "elements": [
                            {
                                "type": "text",
                                "text": "Dang it, we timed this last baby wrong!"
                            }
                        ]
                    }
                ]
            }
        ],
        "team": "T0ZBAEL59",
        "user_team": "T0ZBAEL59",
        "source_team": "T0ZBAEL59",
        "user_profile": {
            "avatar_hash": "7bb5517fdae8",
            "image_72": "https:\/\/avatars.slack-edge.com\/2023-10-06\/6005443083891_7bb5517fdae8974e301c_72.png",
            "first_name": "Chris",
            "real_name": "Chris Lundy",
            "display_name": "",
            "team": "T0ZBAEL59",
            "name": "lundycw09",
            "is_restricted": false,
            "is_ultra_restricted": false
        },
        "thread_ts": "1697853889.302599",
        "parent_user_id": "U03LK5045V0"
    }
]